aegis/__init__.py
aegis/annotation.py
aegis/equivalence.py
aegis/feature.py
aegis/gene.py
aegis/genefunctions.py
aegis/genome.py
aegis/hits.py
aegis/misc_features.py
aegis/plots.py
aegis/subfeatures.py
aegis/tools.py
aegis/transcript.py
aegis/cli/extract.py
aegis/cli/merge.py
aegis/cli/motifs.py
aegis/cli/orthology.py
aegis/cli/overlap.py
aegis/cli/prune.py
aegis/cli/reformat.py
aegis/cli/rename.py
aegis/cli/subset.py
aegis/cli/summary.py
aegis/cli/symbols.py
aegis/cli/tidy.py
aegis/cli/tidy_genome.py
aegis_bio-0.1.7.dist-info/licenses/LICENSE.md
aegis_bio-0.1.7.dist-info/METADATA
aegis_bio-0.1.7.dist-info/WHEEL
aegis_bio-0.1.7.dist-info/entry_points.txt
aegis_bio-0.1.7.dist-info/top_level.txt
aegis_bio-0.1.7.dist-info/RECORD
