Metadata-Version: 2.4
Name: aegis-bio
Version: 0.1.7
Summary: Annotation Extraction Genomic Integration Suite.
Author-email: David Navarro-Payá <david.navarro.paya@gmail.com>, Antonio Santiago <antsanpaj@gmail.com>, Amandine Velt <Amandine.Velt@inrae.fr>
License-Expression: GPL-3.0-or-later
Classifier: Programming Language :: Python :: 3
Classifier: Operating System :: OS Independent
Requires-Python: >=3.7
License-File: LICENSE.md
Requires-Dist: biopython>=1.81
Requires-Dist: colorlover>=0.3.0
Requires-Dist: matplotlib>=3.5.3
Requires-Dist: networkx>=2.6.3
Requires-Dist: pandas>=1.1.5
Requires-Dist: plotly>=5.18.0
Requires-Dist: scipy>=1.7.3
Requires-Dist: tqdm>=4.67.1
Requires-Dist: typer>=0.16.1
Dynamic: license-file
